[
  {
    "Id": "277407",
    "ThreadId": "80905",
    "Html": "<p>How do i make an .exe file to get alvar to run. I have the sdk and everything for it. i am on the last part where it says to build Alvar.sln.bat but theres a problem.</p>",
    "PostedDate": "2010-01-14T17:38:20.927-08:00",
    "UserRole": null,
    "MarkedAsAnswerDate": null
  },
  {
    "Id": "277448",
    "ThreadId": "80905",
    "Html": "<p>You don't need an .exe of ALVAR. You only need its alvar120.dll and alvarplatform120.dll, and cv100.dll, cvaux100.dll, cvcam100.dll, cxcore100.dll, highgui100.dll, and libguide40.dll from the OpenCV 1.0 installation. Then just run Tutorial 8. You don't need to create an .exe from Alvar.sln since it already has dlls for you to use.</p>\r\n<p>Ohan</p>",
    "PostedDate": "2010-01-14T21:15:24.11-08:00",
    "UserRole": "Owner",
    "MarkedAsAnswerDate": null
  },
  {
    "Id": "277562",
    "ThreadId": "80905",
    "Html": "<p>Ok, thanks, but i only have Alvar120.dll and alvarplatform120.dll</p>",
    "PostedDate": "2010-01-15T06:24:10.523-08:00",
    "UserRole": null,
    "MarkedAsAnswerDate": null
  },
  {
    "Id": "277583",
    "ThreadId": "80905",
    "Html": "<p>Nevermind, i have it. Thanks For Helping.</p>",
    "PostedDate": "2010-01-15T07:04:21.957-08:00",
    "UserRole": null,
    "MarkedAsAnswerDate": null
  }
]